setup.cfg
setup.py
ld_micro_vm/__init__.py
ld_micro_vm/ld_micro_vm.py
ld_micro_vm.egg-info/PKG-INFO
ld_micro_vm.egg-info/SOURCES.txt
ld_micro_vm.egg-info/dependency_links.txt
ld_micro_vm.egg-info/not-zip-safe
ld_micro_vm.egg-info/top_level.txt